Workbook

Sheet Start Here
A1: The ROI Trap: Lab Capital Equipment Decisions in Excel + Python
A2: Companion workbook to the video and notebook by Dr. Owasu Brown · all figures are illustrative
B4: What this workbook shows
B5: Part 1 (native Excel) | C5: Every metric is built with ordinary Excel formulas you can inspect: WACC, ROI, payback, IRR, NPV. Change any yellow cell on the Inputs sheet and everything updates.
B6: Part 2 (Python in Excel) | C6: Ten short Python cells add what plain Excel does poorly: an NPV profile, a sensitivity heatmap, a budget optimizer that tests all 4,096 project combinations, k-means clustering, and a 10,000-run Monte Carlo risk model.
B7: Sheet guide
B8: Inputs | C8: The only sheet you need to edit. Yellow cells with blue text are inputs.
B9: WACC | C9: Builds each lab's weighted average cost of capital from its capital structure.
B10: Scenario1 | C10: Same $1M analyzer, three labs: ROI, payback, IRR, NPV, discounted payback, and charts.
B11: NPV_Profile | C11: NPV at every discount rate from 0% to 25%, plus a what-if heatmap (WACC x annual savings).
B12: Scenario2 | C12: The scale trap: a $100K project vs. a $1 project. Three of four metrics pick the wrong one.
B13: Portfolio | C13: Twelve lab equipment requests and a $2.0M budget. Toggle the Fund? column to build your own portfolio.
B14: Python Steps | C14: Step-by-step instructions and the code for each Python cell, one line per row.
B15: Python Lab | C15: Where the Python TABLE results go (green cells).
B16: Python Charts | C16: Where the Python CHART results go (green cells, sized for pictures).
B17: Color legend
B18: Yellow fill, blue text | C18: Input: type your own number here.
B19: Black text | C19: Formula: do not overwrite.
B20: Green fill | C20: Python target cell: enter a =PY() formula here (see Python Steps).
B21: Before you start with Python in Excel
B22: Requirement | C22: Microsoft 365 with Python in Excel enabled (Excel for Windows, Mac, or the web). Python runs in Microsoft's cloud, so you need an internet connection. Nothing to install.
B23: Check it's available | C23: Go to the Formulas tab. If you see Insert Python, you're ready. You can also type =PY( into any cell.
B24: Calculation order | C24: Python cells run left to right, top to bottom, sheet by sheet. That's why the helper functions (Step 1) go in the first green cell: later steps reuse them.
B25: How to enter each Python step (repeat for Steps 1-10)
B26: 1. Go to the target cell | C26: Each step names its target, e.g. 'Python Lab'!B4. Click that green cell.
B27: 2. Start a Python cell | C27: Type =PY( and press Tab, or use Formulas > Insert Python. The cell turns into a Python editor (a green PY badge appears).
B28: 3. Copy the code | C28: On Python Steps, select that step's gray code rows in column B (click the first, Shift+click the last) and press Ctrl+C (Cmd+C on Mac).
B29: 4. Paste and run | C29: Click back into the Python cell, paste with Ctrl+V, then press Ctrl+Enter to run it.
B30: 5. Show the result | C30: Tables: set the output to Excel Value (the output dropdown next to the formula bar, or Ctrl+Alt+Shift+M) so the table spills into the sheet. Charts: also choose Excel Value to place the picture in the cell.
B31: If you see #SPILL! | C31: Something is in the way of the table. Clear the cells below/right of the green cell.
B32: If you see #PYTHON! | C32: Click the cell and open the Diagnostics pane for the error. Most often a line was missed when copying, or an earlier step hasn't been entered yet.
B33: Suggested teaching flow
B34: Live demo order | C34: Inputs > WACC > Scenario1 > NPV_Profile > Scenario2 > Portfolio (all plain Excel), then Python Steps 1-10 to show what Python adds. Change Company C's cost of equity on Inputs and watch both the Excel and Python results update.

Sheet Inputs
A1: Inputs
A2: Edit only the yellow cells. Every other sheet, and every Python step, reads from here.
B4: Scenario 1: automated lab analyzer
B5: Purchase price (Year 0) | C5: 1000000 | D5: Illustrative figures for teaching (not a real quote).
B6: Annual net cash, Years 1-5 | C6: 270000
B7: Corporate tax rate | C7: 0.25
B9: Capital structure by lab
B10: Company | C10: Lab profile | D10: Equity share | E10: Cost of equity | F10: Cost of debt
B11: Company A | C11: Large pharma QC lab | D11: 0.5 | E11: 0.07 | F11: 0.04 | G11: Equity share = E/V. Debt share is 1 minus this.
B12: Company B | C12: Mid-sized contract research lab | D12: 0.5 | E12: 0.14 | F12: 0.08 | G12: Cost of debt is the pre-tax interest rate.
B13: Company C | C13: Venture-backed biotech startup | D13: 0.8 | E13: 0.245 | F13: 0.16
B15: Scenario 2: the scale trap
B16: WACC | C16: 0.1
B17: Project A outlay (assay automation) | C17: 100000
B18: Project A annual cash, Years 1-10 | C18: 50000
B19: Project B outlay (micro-fix) | C19: 1
B20: Project B annual cash, Years 1-10 | C20: 0.6
B23: Portfolio: twelve capital requests
B24: Lab WACC | C24: 0.1
B25: Capital budget | C25: 2000000
B27: Request | C27: Outlay | D27: Annual cash | E27: Life (yrs)
B28: Automated chemistry analyzer | C28: 1000000 | D28: 270000 | E28: 5 | F28: Annual cash is level each year for the life shown. Illustrative figures.
B29: Liquid-handling robot | C29: 250000 | D29: 80000 | E29: 5
B30: LIMS upgrade | C30: 400000 | D30: 110000 | E30: 7
B31: LC-MS/MS system | C31: 800000 | D31: 190000 | E31: 8
B32: Digital pathology scanner | C32: 350000 | D32: 95000 | E32: 6
B33: Barcode label printers | C33: 15000 | D33: 9000 | E33: 4
B34: Pipette calibration kit | C34: 5000 | D34: 3500 | E34: 3
B35: -80°C freezer replacement | C35: 40000 | D35: 12000 | E35: 10
B36: Automated sample storage | C36: 600000 | D36: 75000 | E36: 15
B37: Next-gen sequencer | C37: 900000 | D37: 230000 | E37: 6
B38: Lab HVAC / fume hood upgrade | C38: 500000 | D38: 60000 | E38: 20
B39: Benchtop qPCR | C39: 120000 | D39: 30000 | E39: 5
B41: Monte Carlo (Python Step 10)
B42: Number of simulations | C42: 10000
B43: Annual cash volatility (std. dev.) | C43: 0.15

Sheet WACC
A1: Step 1: What does money cost each lab? (WACC)
A2: WACC = E/V x Cost of equity + D/V x Cost of debt x (1 - tax rate)
B4: Company | C4: Lab profile | D4: E/V | E4: D/V | F4: Cost of equity | G4: Cost of debt | H4: Tax rate | I4: Equity piece | J4: Debt piece (after tax) | K4: WACC
B5: =Inputs!B11 -> Company A | C5: =Inputs!C11 -> Large pharma QC lab | D5: =Inputs!D11 -> 0.5 | E5: =1-D5 -> 0.5 | F5: =Inputs!E11 -> 0.07 | G5: =Inputs!F11 -> 0.04 | H5: =Inputs!$C$7 -> 0.25 | I5: =D5*F5 -> 0.035 | J5: =E5*G5*(1-H5) -> 0.015 | K5: =I5+J5 -> 0.05
B6: =Inputs!B12 -> Company B | C6: =Inputs!C12 -> Mid-sized contract research lab | D6: =Inputs!D12 -> 0.5 | E6: =1-D6 -> 0.5 | F6: =Inputs!E12 -> 0.14 | G6: =Inputs!F12 -> 0.08 | H6: =Inputs!$C$7 -> 0.25 | I6: =D6*F6 -> 0.07 | J6: =E6*G6*(1-H6) -> 0.03 | K6: =I6+J6 -> 0.1
B7: =Inputs!B13 -> Company C | C7: =Inputs!C13 -> Venture-backed biotech startup | D7: =Inputs!D13 -> 0.8 | E7: =1-D7 -> 0.2 | F7: =Inputs!E13 -> 0.245 | G7: =Inputs!F13 -> 0.16 | H7: =Inputs!$C$7 -> 0.25 | I7: =D7*F7 -> 0.196 | J7: =E7*G7*(1-H7) -> 0.024 | K7: =I7+J7 -> 0.22
B9: Worked example (Company A): 50% x 7.0% + 50% x 4.0% x (1 - 25%) = 3.5% + 1.5% = 5.0%
B10: Healthcare note: a nonprofit hospital lab pays no income tax, so set the tax rate to 0% on Inputs.

Sheet Scenario1
A1: Scenario 1: Same $1M analyzer, three labs
A2: ROI, payback and IRR ignore who is buying. NPV discounts at each lab's own WACC.
B4: Cash flows
B5: Year | C5: 0 | D5: 1 | E5: 2 | F5: 3 | G5: 4 | H5: 5
B6: Cash flow (nominal) | C6: =-Inputs!C5 -> -1000000 | D6: =Inputs!$C$6 -> 270000 | E6: =Inputs!$C$6 -> 270000 | F6: =Inputs!$C$6 -> 270000 | G6: =Inputs!$C$6 -> 270000 | H6: =Inputs!$C$6 -> 270000 | K6: Tip: overwrite any single year to model an uneven ramp-up.
B7: Cumulative (nominal) | C7: =SUM($C$6:C6) -> -1000000 | D7: =SUM($C$6:D6) -> -730000 | E7: =SUM($C$6:E6) -> -460000 | F7: =SUM($C$6:F6) -> -190000 | G7: =SUM($C$6:G6) -> 80000 | H7: =SUM($C$6:H6) -> 350000
B9: Present value of each year at each lab's WACC = Cash flow / (1 + WACC)^year
B10: Company | C10: Year 0 | D10: Year 1 | E10: Year 2 | F10: Year 3 | G10: Year 4 | H10: Year 5
B11: =WACC!B5 -> Company A | C11: =C$6/(1+WACC!$K$5)^0 -> -1000000 | D11: =D$6/(1+WACC!$K$5)^1 -> 257142.86 | E11: =E$6/(1+WACC!$K$5)^2 -> 244897.96 | F11: =F$6/(1+WACC!$K$5)^3 -> 233236.15 | G11: =G$6/(1+WACC!$K$5)^4 -> 222129.67 | H11: =H$6/(1+WACC!$K$5)^5 -> 211552.06
B12: =WACC!B6 -> Company B | C12: =C$6/(1+WACC!$K$6)^0 -> -1000000 | D12: =D$6/(1+WACC!$K$6)^1 -> 245454.55 | E12: =E$6/(1+WACC!$K$6)^2 -> 223140.5 | F12: =F$6/(1+WACC!$K$6)^3 -> 202855 | G12: =G$6/(1+WACC!$K$6)^4 -> 184413.63 | H12: =H$6/(1+WACC!$K$6)^5 -> 167648.76
B13: =WACC!B7 -> Company C | C13: =C$6/(1+WACC!$K$7)^0 -> -1000000 | D13: =D$6/(1+WACC!$K$7)^1 -> 221311.48 | E13: =E$6/(1+WACC!$K$7)^2 -> 181402.85 | F13: =F$6/(1+WACC!$K$7)^3 -> 148690.86 | G13: =G$6/(1+WACC!$K$7)^4 -> 121877.75 | H13: =H$6/(1+WACC!$K$7)^5 -> 99899.798
B15: Cumulative present value (where it turns positive = discounted payback)
B16: Company | C16: Year 0 | D16: Year 1 | E16: Year 2 | F16: Year 3 | G16: Year 4 | H16: Year 5
B17: =WACC!B5 -> Company A | C17: =SUM($C11:C11) -> -1000000 | D17: =SUM($C11:D11) -> -742857.14 | E17: =SUM($C11:E11) -> -497959.18 | F17: =SUM($C11:F11) -> -264723.03 | G17: =SUM($C11:G11) -> -42593.364 | H17: =SUM($C11:H11) -> 168958.7
B18: =WACC!B6 -> Company B | C18: =SUM($C12:C12) -> -1000000 | D18: =SUM($C12:D12) -> -754545.45 | E18: =SUM($C12:E12) -> -531404.96 | F18: =SUM($C12:F12) -> -328549.96 | G18: =SUM($C12:G12) -> -144136.33 | H18: =SUM($C12:H12) -> 23512.428
B19: =WACC!B7 -> Company C | C19: =SUM($C13:C13) -> -1000000 | D19: =SUM($C13:D13) -> -778688.52 | E19: =SUM($C13:E13) -> -597285.68 | F19: =SUM($C13:F13) -> -448594.82 | G19: =SUM($C13:G13) -> -326717.06 | H19: =SUM($C13:H13) -> -226817.26
B21: Scorecard
B22: Company | C22: WACC | D22: Simple ROI | E22: Payback (yrs) | F22: Disc. payback (yrs) | G22: IRR | H22: NPV | I22: Profitability index | J22: Decision
B23: =WACC!B5 -> Company A | C23: =WACC!K5 -> 0.05 | D23: =(SUM($D$6:$H$6)+$C$6)/-$C$6 -> 0.35 | E23: =IF(COUNTIF($C$7:$H$7,"<0")=6,"Never",COUNTIF($C$7:$H$7,"<0")-1-INDEX($C$7:$H$7,COUNTIF($C$7:$H$7,"<0"))/INDEX($C$6:$H$6,COUNTIF($C$7:$H$7,"<0")+1)) -> 3.7037037 | F23: =IF(COUNTIF($C$17:$H$17,"<0")=6,"Never",COUNTIF($C$17:$H$17,"<0")-1-INDEX($C$17:$H$17,COUNTIF($C$17:$H$17,"<0"))/INDEX($C$11:$H$11,COUNTIF($C$17:$H$17,"<0")+1)) -> 4.2013375 | G23: =IRR($C$6:$H$6) -> 0.10916175 | H23: =NPV(C23,$D$6:$H$6)+$C$6 -> 168958.7 | I23: =1+H23/-$C$6 -> 1.1689587 | J23: =IF(H23>50000,"Strong accept",IF(H23>0,"Marginal accept","Reject")) -> Strong accept
B24: =WACC!B6 -> Company B | C24: =WACC!K6 -> 0.1 | D24: =(SUM($D$6:$H$6)+$C$6)/-$C$6 -> 0.35 | E24: =IF(COUNTIF($C$7:$H$7,"<0")=6,"Never",COUNTIF($C$7:$H$7,"<0")-1-INDEX($C$7:$H$7,COUNTIF($C$7:$H$7,"<0"))/INDEX($C$6:$H$6,COUNTIF($C$7:$H$7,"<0")+1)) -> 3.7037037 | F24: =IF(COUNTIF($C$18:$H$18,"<0")=6,"Never",COUNTIF($C$18:$H$18,"<0")-1-INDEX($C$18:$H$18,COUNTIF($C$18:$H$18,"<0"))/INDEX($C$12:$H$12,COUNTIF($C$18:$H$18,"<0")+1)) -> 4.8597519 | G24: =IRR($C$6:$H$6) -> 0.10916175 | H24: =NPV(C24,$D$6:$H$6)+$C$6 -> 23512.428 | I24: =1+H24/-$C$6 -> 1.0235124 | J24: =IF(H24>50000,"Strong accept",IF(H24>0,"Marginal accept","Reject")) -> Marginal accept
B25: =WACC!B7 -> Company C | C25: =WACC!K7 -> 0.22 | D25: =(SUM($D$6:$H$6)+$C$6)/-$C$6 -> 0.35 | E25: =IF(COUNTIF($C$7:$H$7,"<0")=6,"Never",COUNTIF($C$7:$H$7,"<0")-1-INDEX($C$7:$H$7,COUNTIF($C$7:$H$7,"<0"))/INDEX($C$6:$H$6,COUNTIF($C$7:$H$7,"<0")+1)) -> 3.7037037 | F25: =IF(COUNTIF($C$19:$H$19,"<0")=6,"Never",COUNTIF($C$19:$H$19,"<0")-1-INDEX($C$19:$H$19,COUNTIF($C$19:$H$19,"<0"))/INDEX($C$13:$H$13,COUNTIF($C$19:$H$19,"<0")+1)) -> Never | G25: =IRR($C$6:$H$6) -> 0.10916175 | H25: =NPV(C25,$D$6:$H$6)+$C$6 -> -226817.26 | I25: =1+H25/-$C$6 -> 0.77318274 | J25: =IF(H25>50000,"Strong accept",IF(H25>0,"Marginal accept","Reject")) -> Reject
B27: Column Simple ROI: ROI = (total inflows - outlay) / outlay. No timing, no WACC.
B28: Column Payback (yrs): Payback = years before the running total turns positive + the fraction of the next year needed.
B29: Column Disc. payback (yrs): Same as payback, but on the present values. 'Never' = the lab never earns its money back in today's dollars.
B30: Column NPV: Excel's NPV() assumes the FIRST value is one year out, so Year 0 is added separately. Including Year 0 inside NPV() is a common mistake.
B31: Column IRR: IRR is a property of the project, so it's the same for every lab.

Sheet NPV_Profile
A1: NPV profile and what-if heatmap
A2: Where the curve crosses zero is the IRR. Labs to the left create value; to the right they destroy it.
B4: Discount rate | C4: Analyzer NPV | E4: Company | F4: WACC | G4: NPV
B5: 0 | C5: =NPV(B5,Scenario1!$D$6:$H$6)+Scenario1!$C$6 -> 350000 | E5: =WACC!B5 -> Company A | F5: =WACC!K5 -> 0.05 | G5: =Scenario1!H23 -> 168958.7
B6: 0.01 | C6: =NPV(B6,Scenario1!$D$6:$H$6)+Scenario1!$C$6 -> 310426.43 | E6: =WACC!B6 -> Company B | F6: =WACC!K6 -> 0.1 | G6: =Scenario1!H24 -> 23512.428
B7: 0.02 | C7: =NPV(B7,Scenario1!$D$6:$H$6)+Scenario1!$C$6 -> 272634.07 | E7: =WACC!B7 -> Company C | F7: =WACC!K7 -> 0.22 | G7: =Scenario1!H25 -> -226817.26
B8: 0.03 | C8: =NPV(B8,Scenario1!$D$6:$H$6)+Scenario1!$C$6 -> 236520.94
B9: 0.04 | C9: =NPV(B9,Scenario1!$D$6:$H$6)+Scenario1!$C$6 -> 201992.03 | E9: IRR | F9: =Scenario1!G23 -> 0.10916175
B10: 0.05 | C10: =NPV(B10,Scenario1!$D$6:$H$6)+Scenario1!$C$6 -> 168958.7
B11: 0.06 | C11: =NPV(B11,Scenario1!$D$6:$H$6)+Scenario1!$C$6 -> 137338.22
B12: 0.07 | C12: =NPV(B12,Scenario1!$D$6:$H$6)+Scenario1!$C$6 -> 107053.31
B13: 0.08 | C13: =NPV(B13,Scenario1!$D$6:$H$6)+Scenario1!$C$6 -> 78031.71
B14: 0.09 | C14: =NPV(B14,Scenario1!$D$6:$H$6)+Scenario1!$C$6 -> 50205.841
B15: 0.1 | C15: =NPV(B15,Scenario1!$D$6:$H$6)+Scenario1!$C$6 -> 23512.428
B16: 0.11 | C16: =NPV(B16,Scenario1!$D$6:$H$6)+Scenario1!$C$6 -> -2107.8052
B17: 0.12 | C17: =NPV(B17,Scenario1!$D$6:$H$6)+Scenario1!$C$6 -> -26710.425
B18: 0.13 | C18: =NPV(B18,Scenario1!$D$6:$H$6)+Scenario1!$C$6 -> -50347.559
B19: 0.14 | C19: =NPV(B19,Scenario1!$D$6:$H$6)+Scenario1!$C$6 -> -73068.138
B20: 0.15 | C20: =NPV(B20,Scenario1!$D$6:$H$6)+Scenario1!$C$6 -> -94918.124
B21: 0.16 | C21: =NPV(B21,Scenario1!$D$6:$H$6)+Scenario1!$C$6 -> -115940.71
... B30: 0.25 | C30: =NPV(B30,Scenario1!$D$6:$H$6)+Scenario1!$C$6 -> -273894.4
B33: What-if heatmap: analyzer NPV for each WACC (across) and annual net cash (down)
B34: Formula in each cell: =-PV(WACC, 5, annual cash) - purchase price (PV of a level 5-year stream minus the outlay)
B36: Annual cash \ WACC | C36: 0.02 | D36: 0.04 | E36: 0.06 | F36: 0.08 | G36: 0.1 | H36: 0.12 | I36: 0.14 | J36: 0.16 | K36: 0.18 | L36: 0.2 | M36: 0.22 | N36: 0.24
B37: 340000 | C37: =-PV(C$36,5,$B37)-Inputs!$C$5 -> 602576.23 | D37: =-PV(D$36,5,$B37)-Inputs!$C$5 -> 513619.59 | E37: =-PV(E$36,5,$B37)-Inputs!$C$5 -> 432203.69 | F37: =-PV(F$36,5,$B37)-Inputs!$C$5 -> 357521.41 | G37: =-PV(G$36,5,$B37)-Inputs!$C$5 -> 288867.5 | H37: =-PV(H$36,5,$B37)-Inputs!$C$5 -> 225623.91 | I37: =-PV(I$36,5,$B37)-Inputs!$C$5 -> 167247.53 | J37: =-PV(J$36,5,$B37)-Inputs!$C$5 -> 113259.84 | ... N37: =-PV(N$36,5,$B37)-Inputs!$C$5 -> -66569.299
B38: 320000 | C38: =-PV(C$36,5,$B38)-Inputs!$C$5 -> 508307.04 | D38: =-PV(D$36,5,$B38)-Inputs!$C$5 -> 424583.15 | E38: =-PV(E$36,5,$B38)-Inputs!$C$5 -> 347956.41 | F38: =-PV(F$36,5,$B38)-Inputs!$C$5 -> 277667.21 | G38: =-PV(G$36,5,$B38)-Inputs!$C$5 -> 213051.77 | H38: =-PV(H$36,5,$B38)-Inputs!$C$5 -> 153528.38 | I38: =-PV(I$36,5,$B38)-Inputs!$C$5 -> 98585.91 | J38: =-PV(J$36,5,$B38)-Inputs!$C$5 -> 47773.969 | ... N38: =-PV(N$36,5,$B38)-Inputs!$C$5 -> -121476.99
B39: 300000 | C39: =-PV(C$36,5,$B39)-Inputs!$C$5 -> 414037.85 | D39: =-PV(D$36,5,$B39)-Inputs!$C$5 -> 335546.7 | E39: =-PV(E$36,5,$B39)-Inputs!$C$5 -> 263709.14 | F39: =-PV(F$36,5,$B39)-Inputs!$C$5 -> 197813.01 | G39: =-PV(G$36,5,$B39)-Inputs!$C$5 -> 137236.03 | H39: =-PV(H$36,5,$B39)-Inputs!$C$5 -> 81432.861 | I39: =-PV(I$36,5,$B39)-Inputs!$C$5 -> 29924.291 | J39: =-PV(J$36,5,$B39)-Inputs!$C$5 -> -17711.904 | ... N39: =-PV(N$36,5,$B39)-Inputs!$C$5 -> -176384.68
B40: 280000 | C40: =-PV(C$36,5,$B40)-Inputs!$C$5 -> 319768.66 | D40: =-PV(D$36,5,$B40)-Inputs!$C$5 -> 246510.25 | E40: =-PV(E$36,5,$B40)-Inputs!$C$5 -> 179461.86 | F40: =-PV(F$36,5,$B40)-Inputs!$C$5 -> 117958.81 | G40: =-PV(G$36,5,$B40)-Inputs!$C$5 -> 61420.295 | H40: =-PV(H$36,5,$B40)-Inputs!$C$5 -> 9337.3367 | I40: =-PV(I$36,5,$B40)-Inputs!$C$5 -> -38737.329 | J40: =-PV(J$36,5,$B40)-Inputs!$C$5 -> -83197.777 | ... N40: =-PV(N$36,5,$B40)-Inputs!$C$5 -> -231292.36
B41: 260000 | C41: =-PV(C$36,5,$B41)-Inputs!$C$5 -> 225499.47 | D41: =-PV(D$36,5,$B41)-Inputs!$C$5 -> 157473.81 | E41: =-PV(E$36,5,$B41)-Inputs!$C$5 -> 95214.584 | F41: =-PV(F$36,5,$B41)-Inputs!$C$5 -> 38104.61 | G41: =-PV(G$36,5,$B41)-Inputs!$C$5 -> -14395.44 | H41: =-PV(H$36,5,$B41)-Inputs!$C$5 -> -62758.187 | I41: =-PV(I$36,5,$B41)-Inputs!$C$5 -> -107398.95 | J41: =-PV(J$36,5,$B41)-Inputs!$C$5 -> -148683.65 | ... N41: =-PV(N$36,5,$B41)-Inputs!$C$5 -> -286200.05
B42: 240000 | C42: =-PV(C$36,5,$B42)-Inputs!$C$5 -> 131230.28 | D42: =-PV(D$36,5,$B42)-Inputs!$C$5 -> 68437.359 | E42: =-PV(E$36,5,$B42)-Inputs!$C$5 -> 10967.309 | F42: =-PV(F$36,5,$B42)-Inputs!$C$5 -> -41749.591 | G42: =-PV(G$36,5,$B42)-Inputs!$C$5 -> -90211.175 | H42: =-PV(H$36,5,$B42)-Inputs!$C$5 -> -134853.71 | I42: =-PV(I$36,5,$B42)-Inputs!$C$5 -> -176060.57 | J42: =-PV(J$36,5,$B42)-Inputs!$C$5 -> -214169.52 | ... N42: =-PV(N$36,5,$B42)-Inputs!$C$5 -> -341107.74
B43: 220000 | C43: =-PV(C$36,5,$B43)-Inputs!$C$5 -> 36961.092 | D43: =-PV(D$36,5,$B43)-Inputs!$C$5 -> -20599.087 | E43: =-PV(E$36,5,$B43)-Inputs!$C$5 -> -73279.967 | F43: =-PV(F$36,5,$B43)-Inputs!$C$5 -> -121603.79 | G43: =-PV(G$36,5,$B43)-Inputs!$C$5 -> -166026.91 | H43: =-PV(H$36,5,$B43)-Inputs!$C$5 -> -206949.24 | I43: =-PV(I$36,5,$B43)-Inputs!$C$5 -> -244722.19 | J43: =-PV(J$36,5,$B43)-Inputs!$C$5 -> -279655.4 | ... N43: =-PV(N$36,5,$B43)-Inputs!$C$5 -> -396015.43
B44: 200000 | C44: =-PV(C$36,5,$B44)-Inputs!$C$5 -> -57308.098 | D44: =-PV(D$36,5,$B44)-Inputs!$C$5 -> -109635.53 | E44: =-PV(E$36,5,$B44)-Inputs!$C$5 -> -157527.24 | F44: =-PV(F$36,5,$B44)-Inputs!$C$5 -> -201457.99 | G44: =-PV(G$36,5,$B44)-Inputs!$C$5 -> -241842.65 | H44: =-PV(H$36,5,$B44)-Inputs!$C$5 -> -279044.76 | I44: =-PV(I$36,5,$B44)-Inputs!$C$5 -> -313383.81 | J44: =-PV(J$36,5,$B44)-Inputs!$C$5 -> -345141.27 | ... N44: =-PV(N$36,5,$B44)-Inputs!$C$5 -> -450923.12
B46: Blue = buy (NPV > 0). Red = don't (NPV < 0). Find your own WACC column to see how much savings you need to break even.

Sheet Scenario2
A1: Scenario 2: The scale trap
A2: One lab, 10% WACC, room for only ONE project. Three of four metrics pick the wrong one.
B4: Year | C4: 0 | D4: 1 | E4: 2 | F4: 3 | G4: 4 | H4: 5 | I4: 6 | J4: 7 | K4: 8 | L4: 9 | M4: 10
B5: Project A: assay automation | C5: =-Inputs!C17 -> -100000 | D5: =Inputs!$C$18 -> 50000 | E5: =Inputs!$C$18 -> 50000 | F5: =Inputs!$C$18 -> 50000 | G5: =Inputs!$C$18 -> 50000 | H5: =Inputs!$C$18 -> 50000 | I5: =Inputs!$C$18 -> 50000 | J5: =Inputs!$C$18 -> 50000 | K5: =Inputs!$C$18 -> 50000 | ... M5: =Inputs!$C$18 -> 50000
B6: Project B: micro-fix | C6: =-Inputs!C19 -> -1 | D6: =Inputs!$C$20 -> 0.6 | E6: =Inputs!$C$20 -> 0.6 | F6: =Inputs!$C$20 -> 0.6 | G6: =Inputs!$C$20 -> 0.6 | H6: =Inputs!$C$20 -> 0.6 | I6: =Inputs!$C$20 -> 0.6 | J6: =Inputs!$C$20 -> 0.6 | K6: =Inputs!$C$20 -> 0.6 | ... M6: =Inputs!$C$20 -> 0.6
B8: Metric | C8: Project A | D8: Project B | E8: Metric picks
B9: Simple ROI | C9: =(SUM(D5:M5)+C5)/-C5 -> 4 | D9: =(SUM(D6:M6)+C6)/-C6 -> 5 | E9: =IF(C9>D9,"Project A","Project B") -> Project B
B10: Payback (yrs) | C10: =-C5/D5 -> 2 | D10: =-C6/D6 -> 1.6666667 | E10: =IF(C10<D10,"Project A","Project B") -> Project B
B11: IRR | C11: =IRR(C5:M5) -> 0.49077766 | D11: =IRR(C6:M6) -> 0.59434641 | E11: =IF(C11>D11,"Project A","Project B") -> Project B
B12: NPV at WACC | C12: =NPV(Inputs!$C$16,D5:M5)+C5 -> 207228.36 | D12: =NPV(Inputs!$C$16,D6:M6)+C6 -> 2.6867403 | E12: =IF(C12>D12,"Project A","Project B") -> Project A
B13: Value difference (A - B) | C13: =C12-D12 -> 207225.67
B14: Payback here = outlay / annual cash, which works because each project's cash is level every year.
B15: Percentages don't pay the bills. Dollars do: only NPV is measured in dollars.

Sheet Portfolio
A1: Portfolio: twelve equipment requests, one $2.0M budget
A2: Toggle the Fund? column (1 = fund, 0 = don't) and watch total value change. Level annual cash for each request's life.
B5: Request | C5: Outlay | D5: Annual cash | E5: Life (yrs) | F5: Simple ROI | G5: Payback (yrs) | H5: IRR | I5: NPV | J5: Rank by ROI | K5: Rank by NPV | L5: Fund? (1/0) | M5: ROI-rule picks | N5: NPV-best picks
B6: =Inputs!B28 -> Automated chemistry analyzer | C6: =Inputs!C28 -> 1000000 | D6: =Inputs!D28 -> 270000 | E6: =Inputs!E28 -> 5 | F6: =(D6*E6-C6)/C6 -> 0.35 | G6: =C6/D6 -> 3.7037037 | H6: =RATE(E6,D6,-C6) -> 0.10916175 | I6: =PV(Inputs!$C$24,E6,-D6)-C6 -> 23512.428 | J6: =RANK(F6,$F$6:$F$17,0) -> 11 | K6: =RANK(I6,$I$6:$I$17,0) -> 7 | L6: 0 | M6: 0 | N6: 0
B7: =Inputs!B29 -> Liquid-handling robot | C7: =Inputs!C29 -> 250000 | D7: =Inputs!D29 -> 80000 | E7: =Inputs!E29 -> 5 | F7: =(D7*E7-C7)/C7 -> 0.6 | G7: =C7/D7 -> 3.125 | H7: =RATE(E7,D7,-C7) -> 0.18030667 | I7: =PV(Inputs!$C$24,E7,-D7)-C7 -> 53262.942 | J7: =RANK(F7,$F$6:$F$17,0) -> 9 | K7: =RANK(I7,$I$6:$I$17,0) -> 5 | L7: 0 | M7: 0 | N7: 1
B8: =Inputs!B30 -> LIMS upgrade | C8: =Inputs!C30 -> 400000 | D8: =Inputs!D30 -> 110000 | E8: =Inputs!E30 -> 7 | F8: =(D8*E8-C8)/C8 -> 0.925 | G8: =C8/D8 -> 3.6363636 | H8: =RATE(E8,D8,-C8) -> 0.19680834 | I8: =PV(Inputs!$C$24,E8,-D8)-C8 -> 135526.07 | J8: =RANK(F8,$F$6:$F$17,0) -> 5 | K8: =RANK(I8,$I$6:$I$17,0) -> 2 | L8: 1 | M8: 1 | N8: 1
B9: =Inputs!B31 -> LC-MS/MS system | C9: =Inputs!C31 -> 800000 | D9: =Inputs!D31 -> 190000 | E9: =Inputs!E31 -> 8 | F9: =(D9*E9-C9)/C9 -> 0.9 | G9: =C9/D9 -> 4.2105263 | H9: =RATE(E9,D9,-C9) -> 0.16974713 | I9: =PV(Inputs!$C$24,E9,-D9)-C9 -> 213635.98 | J9: =RANK(F9,$F$6:$F$17,0) -> 6 | K9: =RANK(I9,$I$6:$I$17,0) -> 1 | L9: 1 | M9: 1 | N9: 1
B10: =Inputs!B32 -> Digital pathology scanner | C10: =Inputs!C32 -> 350000 | D10: =Inputs!D32 -> 95000 | E10: =Inputs!E32 -> 6 | F10: =(D10*E10-C10)/C10 -> 0.62857143 | G10: =C10/D10 -> 3.6842105 | H10: =RATE(E10,D10,-C10) -> 0.16005383 | I10: =PV(Inputs!$C$24,E10,-D10)-C10 -> 63749.766 | J10: =RANK(F10,$F$6:$F$17,0) -> 8 | K10: =RANK(I10,$I$6:$I$17,0) -> 4 | L10: 0 | M10: 0 | N10: 1
B11: =Inputs!B33 -> Barcode label printers | C11: =Inputs!C33 -> 15000 | D11: =Inputs!D33 -> 9000 | E11: =Inputs!E33 -> 4 | F11: =(D11*E11-C11)/C11 -> 1.4 | G11: =C11/D11 -> 1.6666667 | H11: =RATE(E11,D11,-C11) -> 0.47231121 | I11: =PV(Inputs!$C$24,E11,-D11)-C11 -> 13528.789 | J11: =RANK(F11,$F$6:$F$17,0) -> 2 | K11: =RANK(I11,$I$6:$I$17,0) -> 8 | L11: 1 | M11: 1 | N11: 1
B12: =Inputs!B34 -> Pipette calibration kit | C12: =Inputs!C34 -> 5000 | D12: =Inputs!D34 -> 3500 | E12: =Inputs!E34 -> 3 | F12: =(D12*E12-C12)/C12 -> 1.1 | G12: =C12/D12 -> 1.4285714 | H12: =RATE(E12,D12,-C12) -> 0.4871843 | I12: =PV(Inputs!$C$24,E12,-D12)-C12 -> 3703.982 | J12: =RANK(F12,$F$6:$F$17,0) -> 4 | K12: =RANK(I12,$I$6:$I$17,0) -> 10 | L12: 1 | M12: 1 | N12: 1
B13: =Inputs!B35 -> -80°C freezer replacement | C13: =Inputs!C35 -> 40000 | D13: =Inputs!D35 -> 12000 | E13: =Inputs!E35 -> 10 | F13: =(D13*E13-C13)/C13 -> 2 | G13: =C13/D13 -> 3.3333333 | H13: =RATE(E13,D13,-C13) -> 0.27319842 | I13: =PV(Inputs!$C$24,E13,-D13)-C13 -> 33734.805 | J13: =RANK(F13,$F$6:$F$17,0) -> 1 | K13: =RANK(I13,$I$6:$I$17,0) -> 6 | L13: 1 | M13: 1 | N13: 1
B14: =Inputs!B36 -> Automated sample storage | C14: =Inputs!C36 -> 600000 | D14: =Inputs!D36 -> 75000 | E14: =Inputs!E36 -> 15 | F14: =(D14*E14-C14)/C14 -> 0.875 | G14: =C14/D14 -> 8 | H14: =RATE(E14,D14,-C14) -> 0.091282965 | I14: =PV(Inputs!$C$24,E14,-D14)-C14 -> -29544.037 | J14: =RANK(F14,$F$6:$F$17,0) -> 7 | K14: =RANK(I14,$I$6:$I$17,0) -> 12 | L14: 0 | M14: 0 | N14: 0
B15: =Inputs!B37 -> Next-gen sequencer | C15: =Inputs!C37 -> 900000 | D15: =Inputs!D37 -> 230000 | E15: =Inputs!E37 -> 6 | F15: =(D15*E15-C15)/C15 -> 0.53333333 | G15: =C15/D15 -> 3.9130435 | H15: =RATE(E15,D15,-C15) -> 0.13772242 | I15: =PV(Inputs!$C$24,E15,-D15)-C15 -> 101709.96 | J15: =RANK(F15,$F$6:$F$17,0) -> 10 | K15: =RANK(I15,$I$6:$I$17,0) -> 3 | L15: 0 | M15: 0 | N15: 0
B16: =Inputs!B38 -> Lab HVAC / fume hood upgrade | C16: =Inputs!C38 -> 500000 | D16: =Inputs!D38 -> 60000 | E16: =Inputs!E38 -> 20 | F16: =(D16*E16-C16)/C16 -> 1.4 | G16: =C16/D16 -> 8.3333333 | H16: =RATE(E16,D16,-C16) -> 0.10315615 | I16: =PV(Inputs!$C$24,E16,-D16)-C16 -> 10813.823 | J16: =RANK(F16,$F$6:$F$17,0) -> 2 | K16: =RANK(I16,$I$6:$I$17,0) -> 9 | L16: 1 | M16: 1 | N16: 0
B17: =Inputs!B39 -> Benchtop qPCR | C17: =Inputs!C39 -> 120000 | D17: =Inputs!D39 -> 30000 | E17: =Inputs!E39 -> 5 | F17: =(D17*E17-C17)/C17 -> 0.25 | G17: =C17/D17 -> 4 | H17: =RATE(E17,D17,-C17) -> 0.079308261 | I17: =PV(Inputs!$C$24,E17,-D17)-C17 -> -6276.3969 | J17: =RANK(F17,$F$6:$F$17,0) -> 12 | K17: =RANK(I17,$I$6:$I$17,0) -> 11 | L17: 1 | M17: 1 | N17: 0
B19: Portfolio totals | L19: Your picks | M19: ROI rule | N19: NPV best
B20: Capital spent | L20: =SUMPRODUCT($C$6:$C$17,L6:L17) -> 1880000 | M20: =SUMPRODUCT($C$6:$C$17,M6:M17) -> 1880000 | N20: =SUMPRODUCT($C$6:$C$17,N6:N17) -> 1860000
B21: Total NPV (value created) | L21: =SUMPRODUCT($I$6:$I$17,L6:L17) -> 404667.05 | M21: =SUMPRODUCT($I$6:$I$17,M6:M17) -> 404667.05 | N21: =SUMPRODUCT($I$6:$I$17,N6:N17) -> 517142.33
B22: Budget remaining | L22: =Inputs!$C$25-L20 -> 120000 | M22: =Inputs!$C$25-M20 -> 120000 | N22: =Inputs!$C$25-N20 -> 140000
B23: Status | L23: =IF(L20>Inputs!$C$25,"OVER BUDGET","OK") -> OK | M23: =IF(M20>Inputs!$C$25,"OVER BUDGET","OK") -> OK | N23: =IF(N20>Inputs!$C$25,"OVER BUDGET","OK") -> OK
B25: How to use: the Fund? column starts with the ROI rule's picks (fund the highest-ROI requests until the money runs out).
B26: Try the NPV-best set (column N) or your own mix and compare Total NPV. The NPV-best set is the highest-value combination of all 4,096 possibilities, found by Python Step 4 and the notebook.
B27: Why ROI misleads here: the storage and HVAC requests add up 15-20 years of cash without discounting, so their ROI looks great while their NPV is thin or negative.
B28: IRR uses RATE() because each request has level annual cash; NPV uses PV() for the same reason.

Sheet Python Steps
A1: Python in Excel: step-by-step code
A2: For each step: click the target cell, type =PY( , paste the gray code rows, press Ctrl+Enter. Full instructions are on Start Here.
B4: Step 1: Load libraries and define the helper functions
B5: Target cell: 'Python Lab'!B4 Output: Text: Helpers ready
B6: What it does: Defines npv(), irr() and payback() once so every later step can reuse them. Python in Excel doesn't include numpy-financial, so we write these ourselves in a few lines.
B7: Code (select every gray row below, copy, paste into the Python cell):
B8: import numpy as np
B9: import pandas as pd
B10: import matplotlib.pyplot as plt
B12: # NPV: discount each cash flow back to today (flows[0] is Year 0)
B13: def npv(rate, flows):
B14: t = np.arange(len(flows))
B15: return float(np.sum(np.array(flows) / (1 + rate) ** t))
B17: # IRR: find the rate where NPV = 0 by repeatedly halving the search range
... B263: fig

Sheet Python Lab
A1: Python Lab: table results
A2: Green cells are Python targets. Leave the space below and to the right of each one empty so tables can spill.
A4: Step 1 · helpers
A8: Step 2 · WACC table
A15: Step 3 · Scenario 1 scorecard
A22: Step 4 · budget rules

Sheet Python Charts
A1: Python Charts: picture results
A2: Each green cell is sized for a chart. After running a step, set its output to Excel Value to see the picture.
A4: Step 5 · NPV profile
A6: Step 6 · cumulative discounted cash
A8: Step 7 · sensitivity heatmap
A10: Step 8 · Scenario 2 four panels
A12: Step 9 · k-means clusters
A14: Step 10 · Monte Carlo risk
A17: Tip: to make a chart bigger than its cell, right-click the cell > Picture in Cell > Place over Cells.
